{
  "base_url": "http://localhost:5000",
  "endpoints": [
    {
      "method": "GET",
      "path": "/",
      "expect": 200,
      "body": {}
    },
    {
      "method": "GET",
      "path": "/api/health",
      "expect": 200,
      "body": {}
    },
    {
      "method": "POST",
      "path": "/api/job-postings",
      "expect": 200,
      "body": {
        "keywords": "test",
        "description": "Test content here",
        "title": "Test Item"
      }
    },
    {
      "method": "GET",
      "path": "/api/job-postings",
      "expect": 200,
      "body": {
        "keywords": "test",
        "description": "Test content here",
        "title": "Test Item"
      }
    },
    {
      "method": "GET",
      "path": "/api/job-postings/1",
      "expect": 200,
      "body": {}
    },
    {
      "method": "PUT",
      "path": "/api/job-postings/1",
      "expect": 200,
      "body": {}
    },
    {
      "method": "DELETE",
      "path": "/api/job-postings/1",
      "expect": 200,
      "body": {}
    },
    {
      "method": "POST",
      "path": "/api/resumes",
      "expect": 200,
      "body": {
        "file": "test"
      }
    },
    {
      "method": "GET",
      "path": "/api/resumes",
      "expect": 200,
      "body": {
        "file": "test"
      }
    },
    {
      "method": "GET",
      "path": "/api/resumes/1",
      "expect": 200,
      "body": {}
    },
    {
      "method": "POST",
      "path": "/api/resume-analysis",
      "expect": 200,
      "body": {
        "job_posting_id": 1,
        "resume_id": 1
      }
    },
    {
      "method": "GET",
      "path": "/api/candidates",
      "expect": 200,
      "body": {}
    },
    {
      "method": "POST",
      "path": "/api/candidate-search",
      "expect": 200,
      "body": {
        "skills": "test",
        "keywords": "test"
      }
    }
  ]
}